Tikdjo/Tikdjo.py
Tikdjo/__init__.py
tikdjo-0.0.1.dist-info/METADATA
tikdjo-0.0.1.dist-info/WHEEL
tikdjo-0.0.1.dist-info/top_level.txt
tikdjo-0.0.1.dist-info/RECORD
