Metadata-Version: 2.4
Name: Tikdjo
Version: 0.0.1
Summary: TikTok signature generator
Author: djoub
Classifier: Programming Language :: Python :: 3
Classifier: License :: OSI Approved :: MIT License
Classifier: Operating System :: OS Independent
Requires-Python: >=3.7
Requires-Dist: pycryptodome
Requires-Dist: uuid
Dynamic: author
Dynamic: classifier
Dynamic: description
Dynamic: description-content-type
Dynamic: requires-dist
Dynamic: requires-python
Dynamic: summary
